Metadata-Version: 2.0
Name: django-oauth2-provider-unleashed
Version: 0.2.12
Summary: Provide OAuth2 access to your app
Home-page: https://github.com/vikingco/django-oauth2-provider
Author: Unleashed NV
Author-email: operations@unleashed.be
License: MIT
Platform: UNKNOWN
Classifier: Intended Audience :: Developers
Classifier: License :: OSI Approved :: MIT License
Classifier: Programming Language :: Python
Classifier: Operating System :: OS Independent
Classifier: Environment :: Web Environment
Classifier: Framework :: Django
Requires-Dist: shortuuid (>=0.3)
